commands/__init__.py
commands/booking.py
commands/cancel_booking.py
commands/cancel_volunteer.py
commands/options.py
commands/view_calendar.py
commands/volunteer.py
utils/__init__.py
utils/auth.py
utils/cal.py
utils/check_input_error.py
utils/config.py
dbn4_clinic-0.4.0.dist-info/METADATA
dbn4_clinic-0.4.0.dist-info/WHEEL
dbn4_clinic-0.4.0.dist-info/top_level.txt
dbn4_clinic-0.4.0.dist-info/RECORD
