Metadata-Version: 2.1
Name: dbn4-clinic
Version: 0.4.0
Summary: Book a session with volunteer to discuss programming
Author: DBN-04-2023
Requires-Python: >=3.10
